toapi/__init__.py
toapi/api.py
toapi/cli.py
toapi/item.py
toapi/log.py
toapi-2.1.3.dist-info/entry_points.txt
toapi-2.1.3.dist-info/LICENSE
toapi-2.1.3.dist-info/WHEEL
toapi-2.1.3.dist-info/METADATA
toapi-2.1.3.dist-info/RECORD
